pypolsys-0.1.6.dist-info/RECORD
pypolsys-0.1.6.dist-info/LICENSE
pypolsys-0.1.6.dist-info/WHEEL
pypolsys-0.1.6.dist-info/METADATA
pypolsys/version.py
pypolsys/__init__.py
pypolsys/test.py
pypolsys/utils.py
pypolsys/polsys.cpython-312-darwin.so
pypolsys/.dylibs/libgfortran.5.dylib
pypolsys/.dylibs/libquadmath.0.dylib
pypolsys/.dylibs/libgcc_s.1.1.dylib
pypolsys/examples/data/toy_model.npz
