Metadata-Version: 2.1
Name: pypolsys
Version: 0.1.6
Summary: A python wrapper to `POLSYS_PLP` fortran90 package from Layne T. Watson, Steven M. Wise, Andrew J. Sommese, August, 1998.
Author-Email: "B. Nennig" <benoit.nennig@isae-supmeca.fr>
License:                     GNU GENERAL PUBLIC LICENSE
Classifier: Development Status :: 5 - Production/Stable
Classifier: Topic :: Scientific/Engineering
Classifier: Programming Language :: Python :: 3
Classifier: License :: OSI Approved :: GNU General Public License v3 (GPLv3)
Classifier: Operating System :: OS Independent
Project-URL: homepage, https://github.com/nennigb/pypolsys
Requires-Python: >=3.8
Requires-Dist: numpy
Requires-Dist: scipy
Requires-Dist: sympy
